README
setup.py
mt_data_api/__init__.py
mt_data_api/basic_auth.py
mt_data_api/data_api.py
mt_data_api/http_method.py
mt_data_api/version.py
mt_data_api.egg-info/PKG-INFO
mt_data_api.egg-info/SOURCES.txt
mt_data_api.egg-info/dependency_links.txt
mt_data_api.egg-info/top_level.txt