Metadata-Version: 1.1
Name: mt-data-api
Version: 0.0.3
Summary: A port of mt-data-api-sdk-swift.
Home-page: https://github.com/masiuchi/mt-data-api-sdk-python
Author: Masahiro IUCHI
Author-email: masahiro.iuchi@gmail.com
License: MIT License
Keywords: movabletype data-api sdk
Platform: UNKNOWN
Classifier: Development Status :: 2 - Pre-Alpha
Classifier: Intended Audience :: Developers
Classifier: License :: OSI Approved :: MIT License
Classifier: Programming Language :: Python
Classifier: Programming Language :: Python :: 3
Classifier: Programming Language :: Python :: 3.3
Classifier: Programming Language :: Python :: 3.4
Classifier: Programming Language :: Python :: 3.5
Classifier: Programming Language :: Python :: 3.6
